db_connect_mcp/__init__.py
db_connect_mcp/__main__.py
db_connect_mcp/server.py
db_connect_mcp/adapters/__init__.py
db_connect_mcp/adapters/base.py
db_connect_mcp/adapters/clickhouse.py
db_connect_mcp/adapters/mysql.py
db_connect_mcp/adapters/postgresql.py
db_connect_mcp/core/__init__.py
db_connect_mcp/core/analyzer.py
db_connect_mcp/core/connection.py
db_connect_mcp/core/executor.py
db_connect_mcp/core/inspector.py
db_connect_mcp/models/__init__.py
db_connect_mcp/models/capabilities.py
db_connect_mcp/models/config.py
db_connect_mcp/models/database.py
db_connect_mcp/models/profile.py
db_connect_mcp/models/query.py
db_connect_mcp/models/statistics.py
db_connect_mcp/models/table.py
db_connect_mcp-0.2.0.dist-info/METADATA
db_connect_mcp-0.2.0.dist-info/WHEEL
db_connect_mcp-0.2.0.dist-info/entry_points.txt
db_connect_mcp-0.2.0.dist-info/licenses/LICENSE
db_connect_mcp-0.2.0.dist-info/RECORD
