Metadata-Version: 2.4
Name: db-connect-mcp
Version: 0.2.0
Summary: Multi-database MCP server for PostgreSQL, MySQL, and ClickHouse
Project-URL: Homepage, https://github.com/yugui923/db-connect-mcp
Project-URL: Repository, https://github.com/yugui923/db-connect-mcp
Project-URL: Issues, https://github.com/yugui923/db-connect-mcp/issues
Author-email: Yuri Gui <yugui923@users.noreply.github.com>
License: MIT
License-File: LICENSE
Keywords: analysis,claude,clickhouse,data-exploration,database,mcp,mysql,postgresql
Classifier: Development Status :: 4 - Beta
Classifier: Framework :: AsyncIO
Classifier: Intended Audience :: Developers
Classifier: License :: OSI Approved :: MIT License
Classifier: Programming Language :: Python :: 3
Classifier: Programming Language :: Python :: 3.10
Classifier: Programming Language :: Python :: 3.11
Classifier: Programming Language :: Python :: 3.12
Classifier: Programming Language :: Python :: 3.13
Classifier: Topic :: Database
Classifier: Topic :: Software Development :: Libraries :: Python Modules
Requires-Python: >=3.10
Requires-Dist: aiomysql>=0.2.0
Requires-Dist: asyncpg>=0.29.0
Requires-Dist: clickhouse-connect>=0.7.0
Requires-Dist: mcp>=1.0.0
Requires-Dist: orjson>=3.9.0
Requires-Dist: pydantic>=2.0.0
Requires-Dist: python-dotenv>=1.0.0
Requires-Dist: sqlalchemy[asyncio]>=2.0.0
